{
  "metadata": {
    "generated_at": "2026-06-22T22:51:22.278229-04:00",
    "generated_at_formatted": "Monday, June 22, 2026 at 10:51 PM EDT",
    "date": "2026-06-22",
    "timezone": "US/Eastern"
  },
  "summary": {
    "total_games": 5,
    "total_pitchers": 4,
    "games_with_props": 2
  },
  "games": [
    {
      "event_id": "22bf5f58b0fd7173739a6d0fb1bd280e",
      "away_team": "Cleveland Guardians",
      "home_team": "Chicago White Sox",
      "matchup": "Cleveland Guardians @ Chicago White Sox",
      "game_time": "2026-06-22T19:41:00-04:00",
      "game_time_formatted": "07:41 PM EDT",
      "pitchers": []
    },
    {
      "event_id": "2bbd66d60ea2fc31f947643a281cfb84",
      "away_team": "Philadelphia Phillies",
      "home_team": "Washington Nationals",
      "matchup": "Philadelphia Phillies @ Washington Nationals",
      "game_time": "2026-06-22T20:16:00-04:00",
      "game_time_formatted": "08:16 PM EDT",
      "pitchers": []
    },
    {
      "event_id": "4244628ff5c52a85f4e83f8dc171ed4e",
      "away_team": "Boston Red Sox",
      "home_team": "Colorado Rockies",
      "matchup": "Boston Red Sox @ Colorado Rockies",
      "game_time": "2026-06-22T20:41:00-04:00",
      "game_time_formatted": "08:41 PM EDT",
      "pitchers": []
    },
    {
      "event_id": "541d3f8c1e87131917cbf8386a2563f6",
      "away_team": "Baltimore Orioles",
      "home_team": "Los Angeles Angels",
      "matchup": "Baltimore Orioles @ Los Angeles Angels",
      "game_time": "2026-06-22T21:39:00-04:00",
      "game_time_formatted": "09:39 PM EDT",
      "pitchers": [
        {
          "pitcher_name": "Kyle Bradish",
          "strikeout_line": 6.5,
          "consensus_odds": {
            "over": -175,
            "under": 130,
            "over_formatted": "-175",
            "under_formatted": "+130"
          },
          "sportsbooks": [
            "DraftKings"
          ],
          "sportsbook_count": 1,
          "individual_odds": {
            "DraftKings": {
              "over": -175,
              "under": 130
            }
          },
          "raw_odds": {
            "over_odds": [
              -175
            ],
            "under_odds": [
              130
            ]
          }
        },
        {
          "pitcher_name": "Kyle Bradish",
          "strikeout_line": 7.5,
          "consensus_odds": {
            "over": -120,
            "under": -110,
            "over_formatted": "-120",
            "under_formatted": "-110"
          },
          "sportsbooks": [
            "BetMGM"
          ],
          "sportsbook_count": 1,
          "individual_odds": {
            "BetMGM": {
              "over": -120,
              "under": -110
            }
          },
          "raw_odds": {
            "over_odds": [
              -120
            ],
            "under_odds": [
              -110
            ]
          }
        }
      ]
    },
    {
      "event_id": "66c3c3524e444f31fe9fc224ac058351",
      "away_team": "Atlanta Braves",
      "home_team": "San Diego Padres",
      "matchup": "Atlanta Braves @ San Diego Padres",
      "game_time": "2026-06-22T22:11:04-04:00",
      "game_time_formatted": "10:11 PM EDT",
      "pitchers": [
        {
          "pitcher_name": "Grant Holmes",
          "strikeout_line": 4.5,
          "consensus_odds": {
            "over": -133,
            "under": -100,
            "over_formatted": "-133",
            "under_formatted": "-100"
          },
          "sportsbooks": [
            "Fanatics",
            "BetMGM",
            "DraftKings"
          ],
          "sportsbook_count": 3,
          "individual_odds": {
            "DraftKings": {
              "over": -115,
              "under": -120
            },
            "Fanatics": {
              "over": -125,
              "under": -105
            },
            "BetMGM": {
              "over": -165,
              "under": 125
            }
          },
          "raw_odds": {
            "over_odds": [
              -115,
              -125,
              -165
            ],
            "under_odds": [
              -120,
              -105,
              125
            ]
          }
        },
        {
          "pitcher_name": "Michael King",
          "strikeout_line": 4.5,
          "consensus_odds": {
            "over": -130,
            "under": -105,
            "over_formatted": "-130",
            "under_formatted": "-105"
          },
          "sportsbooks": [
            "DraftKings"
          ],
          "sportsbook_count": 1,
          "individual_odds": {
            "DraftKings": {
              "over": -130,
              "under": -105
            }
          },
          "raw_odds": {
            "over_odds": [
              -130
            ],
            "under_odds": [
              -105
            ]
          }
        }
      ]
    }
  ]
}