{
  "metadata": {
    "generated_at": "2025-07-31T16:19:04.403557-04:00",
    "generated_at_formatted": "Thursday, July 31, 2025 at 04:19 PM EDT",
    "date": "2025-07-31",
    "timezone": "US/Eastern"
  },
  "pitchers": [
    {
      "pitcher_name": "Andrew Abbott",
      "strikeout_line": 4.5,
      "consensus_odds": {
        "over": -153,
        "under": 115,
        "over_formatted": "-153",
        "under_formatted": "+115"
      },
      "sportsbooks": [
        "FanDuel",
        "MyBookie.ag",
        "BetRivers",
        "BetOnline.ag"
      ],
      "sportsbook_count": 4,
      "individual_odds": {
        "FanDuel": {
          "over": -152,
          "under": 120
        },
        "BetOnline.ag": {
          "over": -156,
          "under": 120
        },
        "MyBookie.ag": {
          "over": -158,
          "under": 114
        },
        "BetRivers": {
          "over": -148,
          "under": 108
        }
      },
      "raw_odds": {
        "over_odds": [
          -152,
          -156,
          -158,
          -148
        ],
        "under_odds": [
          120,
          120,
          114,
          108
        ]
      },
      "game_info": {
        "matchup": "Atlanta Braves @ Cincinnati Reds",
        "game_time": "07:11 PM EDT",
        "away_team": "Atlanta Braves",
        "home_team": "Cincinnati Reds"
      }
    },
    {
      "pitcher_name": "Andrew Abbott",
      "strikeout_line": 5.5,
      "consensus_odds": {
        "over": 121,
        "under": -162,
        "over_formatted": "+121",
        "under_formatted": "-162"
      },
      "sportsbooks": [
        "BetMGM",
        "Bovada",
        "DraftKings",
        "BetRivers",
        "Fanatics"
      ],
      "sportsbook_count": 5,
      "individual_odds": {
        "Bovada": {
          "over": 115,
          "under": -150
        },
        "DraftKings": {
          "over": 110,
          "under": -145
        },
        "BetMGM": {
          "over": 120,
          "under": -160
        },
        "Fanatics": {
          "over": 120,
          "under": -160
        },
        "BetRivers": {
          "over": 145,
          "under": -205
        }
      },
      "raw_odds": {
        "over_odds": [
          115,
          110,
          120,
          120,
          145
        ],
        "under_odds": [
          -150,
          -145,
          -160,
          -160,
          -205
        ]
      },
      "game_info": {
        "matchup": "Atlanta Braves @ Cincinnati Reds",
        "game_time": "07:11 PM EDT",
        "away_team": "Atlanta Braves",
        "home_team": "Cincinnati Reds"
      }
    },
    {
      "pitcher_name": "Andrew Abbott",
      "strikeout_line": 6.5,
      "consensus_odds": {
        "over": 295,
        "under": -500,
        "over_formatted": "+295",
        "under_formatted": "-500"
      },
      "sportsbooks": [
        "BetRivers"
      ],
      "sportsbook_count": 1,
      "individual_odds": {
        "BetRivers": {
          "over": 295,
          "under": -500
        }
      },
      "raw_odds": {
        "over_odds": [
          295
        ],
        "under_odds": [
          -500
        ]
      },
      "game_info": {
        "matchup": "Atlanta Braves @ Cincinnati Reds",
        "game_time": "07:11 PM EDT",
        "away_team": "Atlanta Braves",
        "home_team": "Cincinnati Reds"
      }
    },
    {
      "pitcher_name": "Andrew Abbott",
      "strikeout_line": 3.5,
      "consensus_odds": {
        "over": -360,
        "under": 235,
        "over_formatted": "-360",
        "under_formatted": "+235"
      },
      "sportsbooks": [
        "BetRivers"
      ],
      "sportsbook_count": 1,
      "individual_odds": {
        "BetRivers": {
          "over": -360,
          "under": 235
        }
      },
      "raw_odds": {
        "over_odds": [
          -360
        ],
        "under_odds": [
          235
        ]
      },
      "game_info": {
        "matchup": "Atlanta Braves @ Cincinnati Reds",
        "game_time": "07:11 PM EDT",
        "away_team": "Atlanta Braves",
        "home_team": "Cincinnati Reds"
      }
    },
    {
      "pitcher_name": "George Kirby",
      "strikeout_line": 5.5,
      "consensus_odds": {
        "over": -142,
        "under": 108,
        "over_formatted": "-142",
        "under_formatted": "+108"
      },
      "sportsbooks": [
        "BetOnline.ag",
        "FanDuel",
        "BetMGM",
        "Bovada",
        "DraftKings",
        "MyBookie.ag",
        "BetRivers",
        "Fanatics"
      ],
      "sportsbook_count": 8,
      "individual_odds": {
        "FanDuel": {
          "over": -134,
          "under": 106
        },
        "BetOnline.ag": {
          "over": -156,
          "under": 120
        },
        "Bovada": {
          "over": -130,
          "under": 100
        },
        "DraftKings": {
          "over": -150,
          "under": 115
        },
        "BetMGM": {
          "over": -130,
          "under": 100
        },
        "MyBookie.ag": {
          "over": -158,
          "under": 114
        },
        "BetRivers": {
          "over": -150,
          "under": 110
        },
        "Fanatics": {
          "over": -130,
          "under": 100
        }
      },
      "raw_odds": {
        "over_odds": [
          -134,
          -156,
          -130,
          -150,
          -130,
          -158,
          -150,
          -130
        ],
        "under_odds": [
          106,
          120,
          100,
          115,
          100,
          114,
          110,
          100
        ]
      },
      "game_info": {
        "matchup": "Texas Rangers @ Seattle Mariners",
        "game_time": "09:41 PM EDT",
        "away_team": "Texas Rangers",
        "home_team": "Seattle Mariners"
      }
    },
    {
      "pitcher_name": "George Kirby",
      "strikeout_line": 7.5,
      "consensus_odds": {
        "over": 270,
        "under": -435,
        "over_formatted": "+270",
        "under_formatted": "-435"
      },
      "sportsbooks": [
        "BetRivers"
      ],
      "sportsbook_count": 1,
      "individual_odds": {
        "BetRivers": {
          "over": 270,
          "under": -435
        }
      },
      "raw_odds": {
        "over_odds": [
          270
        ],
        "under_odds": [
          -435
        ]
      },
      "game_info": {
        "matchup": "Texas Rangers @ Seattle Mariners",
        "game_time": "09:41 PM EDT",
        "away_team": "Texas Rangers",
        "home_team": "Seattle Mariners"
      }
    },
    {
      "pitcher_name": "George Kirby",
      "strikeout_line": 6.5,
      "consensus_odds": {
        "over": 135,
        "under": -190,
        "over_formatted": "+135",
        "under_formatted": "-190"
      },
      "sportsbooks": [
        "BetRivers"
      ],
      "sportsbook_count": 1,
      "individual_odds": {
        "BetRivers": {
          "over": 135,
          "under": -190
        }
      },
      "raw_odds": {
        "over_odds": [
          135
        ],
        "under_odds": [
          -190
        ]
      },
      "game_info": {
        "matchup": "Texas Rangers @ Seattle Mariners",
        "game_time": "09:41 PM EDT",
        "away_team": "Texas Rangers",
        "home_team": "Seattle Mariners"
      }
    },
    {
      "pitcher_name": "George Kirby",
      "strikeout_line": 4.5,
      "consensus_odds": {
        "over": -345,
        "under": 225,
        "over_formatted": "-345",
        "under_formatted": "+225"
      },
      "sportsbooks": [
        "BetRivers"
      ],
      "sportsbook_count": 1,
      "individual_odds": {
        "BetRivers": {
          "over": -345,
          "under": 225
        }
      },
      "raw_odds": {
        "over_odds": [
          -345
        ],
        "under_odds": [
          225
        ]
      },
      "game_info": {
        "matchup": "Texas Rangers @ Seattle Mariners",
        "game_time": "09:41 PM EDT",
        "away_team": "Texas Rangers",
        "home_team": "Seattle Mariners"
      }
    },
    {
      "pitcher_name": "Kumar Rocker",
      "strikeout_line": 4.5,
      "consensus_odds": {
        "over": -139,
        "under": 105,
        "over_formatted": "-139",
        "under_formatted": "+105"
      },
      "sportsbooks": [
        "BetOnline.ag",
        "FanDuel",
        "BetMGM",
        "Bovada",
        "DraftKings",
        "MyBookie.ag",
        "BetRivers",
        "Fanatics"
      ],
      "sportsbook_count": 8,
      "individual_odds": {
        "FanDuel": {
          "over": -142,
          "under": 112
        },
        "BetOnline.ag": {
          "over": -143,
          "under": 110
        },
        "Bovada": {
          "over": -135,
          "under": 105
        },
        "DraftKings": {
          "over": -140,
          "under": 105
        },
        "BetMGM": {
          "over": -135,
          "under": 100
        },
        "MyBookie.ag": {
          "over": -145,
          "under": 105
        },
        "BetRivers": {
          "over": -132,
          "under": -104
        },
        "Fanatics": {
          "over": -140,
          "under": 105
        }
      },
      "raw_odds": {
        "over_odds": [
          -142,
          -143,
          -135,
          -140,
          -135,
          -145,
          -132,
          -140
        ],
        "under_odds": [
          112,
          110,
          105,
          105,
          100,
          105,
          -104,
          105
        ]
      },
      "game_info": {
        "matchup": "Texas Rangers @ Seattle Mariners",
        "game_time": "09:41 PM EDT",
        "away_team": "Texas Rangers",
        "home_team": "Seattle Mariners"
      }
    },
    {
      "pitcher_name": "Kumar Rocker",
      "strikeout_line": 3.5,
      "consensus_odds": {
        "over": -286,
        "under": 195,
        "over_formatted": "-286",
        "under_formatted": "+195"
      },
      "sportsbooks": [
        "BetRivers"
      ],
      "sportsbook_count": 1,
      "individual_odds": {
        "BetRivers": {
          "over": -286,
          "under": 195
        }
      },
      "raw_odds": {
        "over_odds": [
          -286
        ],
        "under_odds": [
          195
        ]
      },
      "game_info": {
        "matchup": "Texas Rangers @ Seattle Mariners",
        "game_time": "09:41 PM EDT",
        "away_team": "Texas Rangers",
        "home_team": "Seattle Mariners"
      }
    },
    {
      "pitcher_name": "Kumar Rocker",
      "strikeout_line": 5.5,
      "consensus_odds": {
        "over": 155,
        "under": -225,
        "over_formatted": "+155",
        "under_formatted": "-225"
      },
      "sportsbooks": [
        "BetRivers"
      ],
      "sportsbook_count": 1,
      "individual_odds": {
        "BetRivers": {
          "over": 155,
          "under": -225
        }
      },
      "raw_odds": {
        "over_odds": [
          155
        ],
        "under_odds": [
          -225
        ]
      },
      "game_info": {
        "matchup": "Texas Rangers @ Seattle Mariners",
        "game_time": "09:41 PM EDT",
        "away_team": "Texas Rangers",
        "home_team": "Seattle Mariners"
      }
    }
  ]
}