{
  "metadata": {
    "generated_at": "2025-07-06T18:15:55.910027-04:00",
    "generated_at_formatted": "Sunday, July 06, 2025 at 06:15 PM EDT",
    "date": "2025-07-06",
    "timezone": "US/Eastern"
  },
  "summary": {
    "total_games": 6,
    "total_pitchers": 20,
    "games_with_props": 3
  },
  "games": [
    {
      "event_id": "82eb6c70a6aa4b80b126e9d43d8e3dda",
      "away_team": "Kansas City Royals",
      "home_team": "Arizona Diamondbacks",
      "matchup": "Kansas City Royals @ Arizona Diamondbacks",
      "game_time": "2025-07-06T16:11:00-04:00",
      "game_time_formatted": "04:11 PM EDT",
      "pitchers": []
    },
    {
      "event_id": "0728d1ce73366e7842682442f7f4b905",
      "away_team": "Houston Astros",
      "home_team": "Los Angeles Dodgers",
      "matchup": "Houston Astros @ Los Angeles Dodgers",
      "game_time": "2025-07-06T16:11:00-04:00",
      "game_time_formatted": "04:11 PM EDT",
      "pitchers": []
    },
    {
      "event_id": "0555850029b7e6e3167adef31e925930",
      "away_team": "Pittsburgh Pirates",
      "home_team": "Seattle Mariners",
      "matchup": "Pittsburgh Pirates @ Seattle Mariners",
      "game_time": "2025-07-06T16:11:00-04:00",
      "game_time_formatted": "04:11 PM EDT",
      "pitchers": []
    },
    {
      "event_id": "0228da0762968ce7fa21c469a5a2e8de",
      "away_team": "St. Louis Cardinals",
      "home_team": "Chicago Cubs",
      "matchup": "St. Louis Cardinals @ Chicago Cubs",
      "game_time": "2025-07-06T18:40:00-04:00",
      "game_time_formatted": "06:40 PM EDT",
      "pitchers": [
        {
          "pitcher_name": "Erick Fedde",
          "strikeout_line": 3.5,
          "consensus_odds": {
            "over": -140,
            "under": 106,
            "over_formatted": "-140",
            "under_formatted": "+106"
          },
          "sportsbooks": [
            "BetMGM",
            "DraftKings",
            "BetRivers",
            "BetOnline.ag",
            "MyBookie.ag",
            "Bovada",
            "FanDuel",
            "Fanatics"
          ],
          "sportsbook_count": 8,
          "individual_odds": {
            "FanDuel": {
              "over": -146,
              "under": 114
            },
            "MyBookie.ag": {
              "over": -133,
              "under": -104
            },
            "BetOnline.ag": {
              "over": -130,
              "under": 100
            },
            "DraftKings": {
              "over": -145,
              "under": 115
            },
            "Bovada": {
              "over": -145,
              "under": 110
            },
            "BetMGM": {
              "over": -140,
              "under": 105
            },
            "BetRivers": {
              "over": -139,
              "under": 102
            },
            "Fanatics": {
              "over": -145,
              "under": 110
            }
          },
          "raw_odds": {
            "over_odds": [
              -146,
              -133,
              -130,
              -145,
              -145,
              -140,
              -139,
              -145
            ],
            "under_odds": [
              114,
              -104,
              100,
              115,
              110,
              105,
              102,
              110
            ]
          }
        },
        {
          "pitcher_name": "Erick Fedde",
          "strikeout_line": 2.5,
          "consensus_odds": {
            "over": -360,
            "under": 235,
            "over_formatted": "-360",
            "under_formatted": "+235"
          },
          "sportsbooks": [
            "BetRivers"
          ],
          "sportsbook_count": 1,
          "individual_odds": {
            "BetRivers": {
              "over": -360,
              "under": 235
            }
          },
          "raw_odds": {
            "over_odds": [
              -360
            ],
            "under_odds": [
              235
            ]
          }
        },
        {
          "pitcher_name": "Erick Fedde",
          "strikeout_line": 4.5,
          "consensus_odds": {
            "over": 160,
            "under": -230,
            "over_formatted": "+160",
            "under_formatted": "-230"
          },
          "sportsbooks": [
            "BetRivers"
          ],
          "sportsbook_count": 1,
          "individual_odds": {
            "BetRivers": {
              "over": 160,
              "under": -230
            }
          },
          "raw_odds": {
            "over_odds": [
              160
            ],
            "under_odds": [
              -230
            ]
          }
        },
        {
          "pitcher_name": "Erick Fedde",
          "strikeout_line": 5.5,
          "consensus_odds": {
            "over": 350,
            "under": -625,
            "over_formatted": "+350",
            "under_formatted": "-625"
          },
          "sportsbooks": [
            "BetRivers"
          ],
          "sportsbook_count": 1,
          "individual_odds": {
            "BetRivers": {
              "over": 350,
              "under": -625
            }
          },
          "raw_odds": {
            "over_odds": [
              350
            ],
            "under_odds": [
              -625
            ]
          }
        },
        {
          "pitcher_name": "Matthew Boyd",
          "strikeout_line": 5.5,
          "consensus_odds": {
            "over": 111,
            "under": -146,
            "over_formatted": "+111",
            "under_formatted": "-146"
          },
          "sportsbooks": [
            "BetMGM",
            "DraftKings",
            "BetRivers",
            "BetOnline.ag",
            "MyBookie.ag",
            "Bovada",
            "FanDuel",
            "Fanatics"
          ],
          "sportsbook_count": 8,
          "individual_odds": {
            "FanDuel": {
              "over": 118,
              "under": -150
            },
            "MyBookie.ag": {
              "over": 114,
              "under": -158
            },
            "BetOnline.ag": {
              "over": 120,
              "under": -156
            },
            "DraftKings": {
              "over": 105,
              "under": -135
            },
            "Bovada": {
              "over": 115,
              "under": -150
            },
            "BetMGM": {
              "over": 100,
              "under": -130
            },
            "BetRivers": {
              "over": 107,
              "under": -143
            },
            "Fanatics": {
              "over": 110,
              "under": -145
            }
          },
          "raw_odds": {
            "over_odds": [
              118,
              114,
              120,
              105,
              115,
              100,
              107,
              110
            ],
            "under_odds": [
              -150,
              -158,
              -156,
              -135,
              -150,
              -130,
              -143,
              -145
            ]
          }
        },
        {
          "pitcher_name": "Matthew Boyd",
          "strikeout_line": 6.5,
          "consensus_odds": {
            "over": 225,
            "under": -335,
            "over_formatted": "+225",
            "under_formatted": "-335"
          },
          "sportsbooks": [
            "BetRivers"
          ],
          "sportsbook_count": 1,
          "individual_odds": {
            "BetRivers": {
              "over": 225,
              "under": -335
            }
          },
          "raw_odds": {
            "over_odds": [
              225
            ],
            "under_odds": [
              -335
            ]
          }
        },
        {
          "pitcher_name": "Matthew Boyd",
          "strikeout_line": 3.5,
          "consensus_odds": {
            "over": -530,
            "under": 310,
            "over_formatted": "-530",
            "under_formatted": "+310"
          },
          "sportsbooks": [
            "BetRivers"
          ],
          "sportsbook_count": 1,
          "individual_odds": {
            "BetRivers": {
              "over": -530,
              "under": 310
            }
          },
          "raw_odds": {
            "over_odds": [
              -530
            ],
            "under_odds": [
              310
            ]
          }
        },
        {
          "pitcher_name": "Matthew Boyd",
          "strikeout_line": 4.5,
          "consensus_odds": {
            "over": -205,
            "under": 145,
            "over_formatted": "-205",
            "under_formatted": "+145"
          },
          "sportsbooks": [
            "BetRivers"
          ],
          "sportsbook_count": 1,
          "individual_odds": {
            "BetRivers": {
              "over": -205,
              "under": 145
            }
          },
          "raw_odds": {
            "over_odds": [
              -205
            ],
            "under_odds": [
              145
            ]
          }
        }
      ]
    },
    {
      "event_id": "ef536ec52a1340743269ee8191ef239e",
      "away_team": "Texas Rangers",
      "home_team": "San Diego Padres",
      "matchup": "Texas Rangers @ San Diego Padres",
      "game_time": "2025-07-06T21:11:00-04:00",
      "game_time_formatted": "09:11 PM EDT",
      "pitchers": [
        {
          "pitcher_name": "Jack Leiter",
          "strikeout_line": 3.5,
          "consensus_odds": {
            "over": -156,
            "under": 118,
            "over_formatted": "-156",
            "under_formatted": "+118"
          },
          "sportsbooks": [
            "BetMGM",
            "DraftKings",
            "BetRivers",
            "MyBookie.ag",
            "Bovada",
            "FanDuel",
            "Fanatics"
          ],
          "sportsbook_count": 7,
          "individual_odds": {
            "FanDuel": {
              "over": -150,
              "under": 118
            },
            "Fanatics": {
              "over": -145,
              "under": 110
            },
            "MyBookie.ag": {
              "over": -156,
              "under": 113
            },
            "DraftKings": {
              "over": -145,
              "under": 115
            },
            "BetRivers": {
              "over": -177,
              "under": 128
            },
            "BetMGM": {
              "over": -160,
              "under": 125
            },
            "Bovada": {
              "over": -160,
              "under": 120
            }
          },
          "raw_odds": {
            "over_odds": [
              -150,
              -145,
              -156,
              -145,
              -177,
              -160,
              -160
            ],
            "under_odds": [
              118,
              110,
              113,
              115,
              128,
              125,
              120
            ]
          }
        },
        {
          "pitcher_name": "Jack Leiter",
          "strikeout_line": 5.5,
          "consensus_odds": {
            "over": 275,
            "under": -435,
            "over_formatted": "+275",
            "under_formatted": "-435"
          },
          "sportsbooks": [
            "BetRivers"
          ],
          "sportsbook_count": 1,
          "individual_odds": {
            "BetRivers": {
              "over": 275,
              "under": -435
            }
          },
          "raw_odds": {
            "over_odds": [
              275
            ],
            "under_odds": [
              -435
            ]
          }
        },
        {
          "pitcher_name": "Jack Leiter",
          "strikeout_line": 4.5,
          "consensus_odds": {
            "over": 128,
            "under": -175,
            "over_formatted": "+128",
            "under_formatted": "-175"
          },
          "sportsbooks": [
            "BetRivers"
          ],
          "sportsbook_count": 1,
          "individual_odds": {
            "BetRivers": {
              "over": 128,
              "under": -175
            }
          },
          "raw_odds": {
            "over_odds": [
              128
            ],
            "under_odds": [
              -175
            ]
          }
        },
        {
          "pitcher_name": "Jack Leiter",
          "strikeout_line": 2.5,
          "consensus_odds": {
            "over": -455,
            "under": 290,
            "over_formatted": "-455",
            "under_formatted": "+290"
          },
          "sportsbooks": [
            "BetRivers"
          ],
          "sportsbook_count": 1,
          "individual_odds": {
            "BetRivers": {
              "over": -455,
              "under": 290
            }
          },
          "raw_odds": {
            "over_odds": [
              -455
            ],
            "under_odds": [
              290
            ]
          }
        }
      ]
    },
    {
      "event_id": "0173ea4ccbccc3703ec6bab7f0d41de0",
      "away_team": "San Francisco Giants",
      "home_team": "Oakland Athletics",
      "matchup": "San Francisco Giants @ Oakland Athletics",
      "game_time": "2025-07-06T22:06:00-04:00",
      "game_time_formatted": "10:06 PM EDT",
      "pitchers": [
        {
          "pitcher_name": "Hayden Birdsong",
          "strikeout_line": 5.5,
          "consensus_odds": {
            "over": -136,
            "under": 103,
            "over_formatted": "-136",
            "under_formatted": "+103"
          },
          "sportsbooks": [
            "BetMGM",
            "DraftKings",
            "BetRivers",
            "BetOnline.ag",
            "MyBookie.ag",
            "Bovada",
            "FanDuel",
            "Fanatics"
          ],
          "sportsbook_count": 8,
          "individual_odds": {
            "FanDuel": {
              "over": -130,
              "under": 102
            },
            "MyBookie.ag": {
              "over": -135,
              "under": -102
            },
            "DraftKings": {
              "over": -135,
              "under": 100
            },
            "BetOnline.ag": {
              "over": -130,
              "under": 101
            },
            "Bovada": {
              "over": -135,
              "under": 105
            },
            "BetMGM": {
              "over": -140,
              "under": 105
            },
            "BetRivers": {
              "over": -152,
              "under": 112
            },
            "Fanatics": {
              "over": -130,
              "under": 100
            }
          },
          "raw_odds": {
            "over_odds": [
              -130,
              -135,
              -135,
              -130,
              -135,
              -140,
              -152,
              -130
            ],
            "under_odds": [
              102,
              -102,
              100,
              101,
              105,
              105,
              112,
              100
            ]
          }
        },
        {
          "pitcher_name": "Hayden Birdsong",
          "strikeout_line": 7.5,
          "consensus_odds": {
            "over": 235,
            "under": -360,
            "over_formatted": "+235",
            "under_formatted": "-360"
          },
          "sportsbooks": [
            "BetRivers"
          ],
          "sportsbook_count": 1,
          "individual_odds": {
            "BetRivers": {
              "over": 235,
              "under": -360
            }
          },
          "raw_odds": {
            "over_odds": [
              235
            ],
            "under_odds": [
              -360
            ]
          }
        },
        {
          "pitcher_name": "Hayden Birdsong",
          "strikeout_line": 6.5,
          "consensus_odds": {
            "over": 125,
            "under": -175,
            "over_formatted": "+125",
            "under_formatted": "-175"
          },
          "sportsbooks": [
            "BetRivers"
          ],
          "sportsbook_count": 1,
          "individual_odds": {
            "BetRivers": {
              "over": 125,
              "under": -175
            }
          },
          "raw_odds": {
            "over_odds": [
              125
            ],
            "under_odds": [
              -175
            ]
          }
        },
        {
          "pitcher_name": "Hayden Birdsong",
          "strikeout_line": 4.5,
          "consensus_odds": {
            "over": -305,
            "under": 205,
            "over_formatted": "-305",
            "under_formatted": "+205"
          },
          "sportsbooks": [
            "BetRivers"
          ],
          "sportsbook_count": 1,
          "individual_odds": {
            "BetRivers": {
              "over": -305,
              "under": 205
            }
          },
          "raw_odds": {
            "over_odds": [
              -305
            ],
            "under_odds": [
              205
            ]
          }
        },
        {
          "pitcher_name": "Jacob Lopez",
          "strikeout_line": 5.5,
          "consensus_odds": {
            "over": 115,
            "under": -151,
            "over_formatted": "+115",
            "under_formatted": "-151"
          },
          "sportsbooks": [
            "BetMGM",
            "DraftKings",
            "BetRivers",
            "BetOnline.ag",
            "MyBookie.ag",
            "Bovada",
            "FanDuel",
            "Fanatics"
          ],
          "sportsbook_count": 8,
          "individual_odds": {
            "FanDuel": {
              "over": 110,
              "under": -140
            },
            "MyBookie.ag": {
              "over": 109,
              "under": -152
            },
            "DraftKings": {
              "over": 115,
              "under": -145
            },
            "BetOnline.ag": {
              "over": 115,
              "under": -149
            },
            "Bovada": {
              "over": 115,
              "under": -150
            },
            "BetMGM": {
              "over": 120,
              "under": -155
            },
            "BetRivers": {
              "over": 118,
              "under": -159
            },
            "Fanatics": {
              "over": 120,
              "under": -160
            }
          },
          "raw_odds": {
            "over_odds": [
              110,
              109,
              115,
              115,
              115,
              120,
              118,
              120
            ],
            "under_odds": [
              -140,
              -152,
              -145,
              -149,
              -150,
              -155,
              -159,
              -160
            ]
          }
        },
        {
          "pitcher_name": "Jacob Lopez",
          "strikeout_line": 4.5,
          "consensus_odds": {
            "over": -180,
            "under": 132,
            "over_formatted": "-180",
            "under_formatted": "+132"
          },
          "sportsbooks": [
            "BetRivers"
          ],
          "sportsbook_count": 1,
          "individual_odds": {
            "BetRivers": {
              "over": -180,
              "under": 132
            }
          },
          "raw_odds": {
            "over_odds": [
              -180
            ],
            "under_odds": [
              132
            ]
          }
        },
        {
          "pitcher_name": "Jacob Lopez",
          "strikeout_line": 3.5,
          "consensus_odds": {
            "over": -435,
            "under": 270,
            "over_formatted": "-435",
            "under_formatted": "+270"
          },
          "sportsbooks": [
            "BetRivers"
          ],
          "sportsbook_count": 1,
          "individual_odds": {
            "BetRivers": {
              "over": -435,
              "under": 270
            }
          },
          "raw_odds": {
            "over_odds": [
              -435
            ],
            "under_odds": [
              270
            ]
          }
        },
        {
          "pitcher_name": "Jacob Lopez",
          "strikeout_line": 6.5,
          "consensus_odds": {
            "over": 235,
            "under": -375,
            "over_formatted": "+235",
            "under_formatted": "-375"
          },
          "sportsbooks": [
            "BetRivers"
          ],
          "sportsbook_count": 1,
          "individual_odds": {
            "BetRivers": {
              "over": 235,
              "under": -375
            }
          },
          "raw_odds": {
            "over_odds": [
              235
            ],
            "under_odds": [
              -375
            ]
          }
        }
      ]
    }
  ]
}